irec/__init__.py
irec/environment/__init__.py
irec/environment/dataset.py
irec/utils/Factory.py
irec/utils/GridSearch.py
irec/utils/__init__.py
irec/utils/constants.py
irec/utils/splitters.py
irec/utils/utils.py
tests/__init__.py
tests/bdd/__init__.py
tests/bdd/steps/__init__.py
tests/bdd/steps/given.py
tests/bdd/steps/then.py
tests/bdd/steps/when.py
tests/unit/__init__.py
tests/unit/test_mf.py
tests/unit/test_value_functions.py
irec-1.2.8.dist-info/LICENSE
irec-1.2.8.dist-info/METADATA
irec-1.2.8.dist-info/WHEEL
irec-1.2.8.dist-info/top_level.txt
irec-1.2.8.dist-info/RECORD
