Metadata-Version: 2.1
Name: irec
Version: 1.2.8
Summary: Reinforcement Learning Recommender Systems Framework
Home-page: https://github.com/irec-org/irec
Author-email: werneck@aluno.ufsj.edu.br, thiagosilva@aluno.ufsj.edu.br, ncsilvaa@dcc.ufmg.br
Project-URL: Bug Tracker, https://github.com/irec-org/irec/issues
Keywords: recommender,recommendation,reinforcement learning,machine learning,framework,library
Classifier: Programming Language :: Python :: 3
Classifier: Programming Language :: Python :: 3.8
Classifier: License :: OSI Approved :: MIT License
Classifier: Intended Audience :: Developers
Classifier: Topic :: Software Development :: Build Tools
Requires-Python: >=3.8
License-File: LICENSE
Requires-Dist: pyyaml
Requires-Dist: joblib
Requires-Dist: matplotlib
Requires-Dist: numba
Requires-Dist: numpy
Requires-Dist: pandas
Requires-Dist: scikit-learn
Requires-Dist: scipy
Requires-Dist: sklearn
Requires-Dist: threadpoolctl (>=3.0.0)
Requires-Dist: tqdm (>=4.62.3)
Requires-Dist: mlflow
Requires-Dist: cachetools
Provides-Extra: nn
Requires-Dist: keras ; extra == 'nn'
Requires-Dist: tensorflow ; extra == 'nn'
Provides-Extra: testing
Requires-Dist: pytest (>=6.0) ; extra == 'testing'
Requires-Dist: pytest-cov (>=2.0) ; extra == 'testing'
Requires-Dist: mypy (>=0.910) ; extra == 'testing'
Requires-Dist: flake8 (>=3.8) ; extra == 'testing'
Requires-Dist: tox (>=3.24) ; extra == 'testing'
Requires-Dist: types-PyYAML ; extra == 'testing'
Requires-Dist: types-cachetools ; extra == 'testing'
